nonebot_plugin_savepic-0.6.1.dist-info/METADATA
nonebot_plugin_savepic-0.6.1.dist-info/WHEEL
nonebot_plugin_savepic-0.6.1.dist-info/entry_points.txt
nonebot_plugin_savepic-0.6.1.dist-info/licenses/LICENSE
nonebot_plugin_savepic/__init__.py
nonebot_plugin_savepic/command.py
nonebot_plugin_savepic/config.py
nonebot_plugin_savepic/core/__init__.py
nonebot_plugin_savepic/core/error.py
nonebot_plugin_savepic/core/fileio.py
nonebot_plugin_savepic/core/sql.py
nonebot_plugin_savepic/core/types.py
nonebot_plugin_savepic/core/utils.py
nonebot_plugin_savepic/listpic.py
nonebot_plugin_savepic/mvpic.py
nonebot_plugin_savepic/rule.py
nonebot_plugin_savepic-0.6.1.dist-info/RECORD
