Metadata-Version: 2.1
Name: nonebot-plugin-savepic
Version: 0.6.1
Summary: 保存表情包（语录）与随机出图
Author-Email: Yan <1964649083@qq.com>
License: MIT
Project-URL: homepage, https://github.com/Yan-Zero/nonebot-plugin-savepic
Requires-Python: <4.0,>=3.11
Requires-Dist: nonebot2<3.0.0,>=2.4.0
Requires-Dist: asyncpg<1.0.0,>=0.28.0
Requires-Dist: nonebot-adapter-onebot<3.0.0,>=2.4.6
Requires-Dist: numpy<3.0.0,>=2.1.3
Requires-Dist: httpx<1.0.0,>=0.28.0
Requires-Dist: nonebot-plugin-alconna>=0.59.4
